<?xml version="1.0" encoding="UTF-8" standalone="yes"?><sst xmlns="http://schemas.openxmlformats.org/spreadsheetml/2006/main" count="136" uniqueCount="112"><si><t>item</t></si><si><t>value</t></si><si><t>description</t></si><si><t>required_sheet</t></si><si><t>participants</t></si><si><t>이 시트만 채워주시면 됩니다.</t></si><si><t>required_columns</t></si><si><t>participant_id | name_ko | team_name | group_name</t></si><si><t>이 4개 컬럼만 입력하면 자동 매칭이 가능합니다.</t></si><si><t>matching_rule_1</t></si><si><t>same_group_only</t></si><si><t>같은 group_name 안에서만 Peer 대상을 생성합니다.</t></si><si><t>matching_rule_2</t></si><si><t>exclude_self</t></si><si><t>본인은 본인을 평가하지 않습니다.</t></si><si><t>matching_rule_3</t></si><si><t>max_4_targets</t></si><si><t>1인당 최대 4명까지만 평가 대상으로 배정합니다.</t></si><si><t>matching_rule_4</t></si><si><t>group_size_varies</t></si><si><t>그룹 인원수가 달라도 자동 처리합니다. 그룹 인원이 5명 이하면 자기 자신 제외 전원을 배정하고, 6명 이상이면 최대 4명까지만 배정합니다.</t></si><si><t>note</t></si><si><t>stable_id_required</t></si><si><t>participant_id는 반드시 고유값이어야 합니다. 예: TL001</t></si><si><t>delivery</t></si><si><t>이 파일을 채워서 전달해주시면 제가 peer_assignments를 자동 생성해드릴 수 있습니다.</t></si><si><t>participant_id</t></si><si><t>name_ko</t></si><si><t>team_name</t></si><si><t>group_name</t></si><si><t>notes</t></si><si><t>TL001</t></si><si><t>방경석</t></si><si><t>Green성장전략팀</t></si><si><t>2조</t></si><si><t>TL002</t></si><si><t>고인석</t></si><si><t>Global최적화팀</t></si><si><t>1조</t></si><si><t></t></si><si><t>TL003</t></si><si><t>이승희</t></si><si><t>브랜드Communication팀</t></si><si><t>TL004</t></si><si><t>권완섭</t></si><si><t>기술전략팀</t></si><si><t>TL005</t></si><si><t>윤원진</t></si><si><t>HVAC사업팀</t></si><si><t>TL006</t></si><si><t>박세준</t></si><si><t>e-Thermal사업팀</t></si><si><t>TL007</t></si><si><t>윤정식</t></si><si><t>e-Drive팀</t></si><si><t>TL008</t></si><si><t>김동현</t></si><si><t>e-Fluids해외사업팀</t></si><si><t>TL009</t></si><si><t>이응복</t></si><si><t>e-Fluids국내사업팀</t></si><si><t>TL010</t></si><si><t>문필규</t></si><si><t>기유전략팀</t></si><si><t>3조</t></si><si><t>TL011</t></si><si><t>오승진</t></si><si><t>기유Value-up팀</t></si><si><t>TL012</t></si><si><t>서상원</t></si><si><t>Sustainable기유팀</t></si><si><t>TL013</t></si><si><t>남기욱</t></si><si><t>기유마케팅팀</t></si><si><t>TL014</t></si><si><t>유태훈</t></si><si><t>기유최적화팀</t></si><si><t>TL015</t></si><si><t>김석원</t></si><si><t>기유SCM팀</t></si><si><t>TL016</t></si><si><t>조형준</t></si><si><t>경영전략팀</t></si><si><t>4조</t></si><si><t>TL017</t></si><si><t>이승호</t></si><si><t>경영관리팀</t></si><si><t>TL018</t></si><si><t>김일권</t></si><si><t>ESG기획팀</t></si><si><t>TL019</t></si><si><t>최은영</t></si><si><t>법무팀</t></si><si><t>TL020</t></si><si><t>전재욱</t></si><si><t>엔무브생산기술팀</t></si><si><t>5조</t></si><si><t>TL021</t></si><si><t>강태현</t></si><si><t>SHE생산관리팀</t></si><si><t>TL022</t></si><si><t>최원근</t></si><si><t>윤활유생산팀</t></si><si><t>TL023</t></si><si><t>이장헌</t></si><si><t>기유생산1팀</t></si><si><t>TL024</t></si><si><t>김명국</t></si><si><t>기유생산2팀</t></si><si><t>TL025</t></si><si><t>이지원</t></si><si><t>기업문화팀</t></si></sst>